[
  {
    "id": 1,
    "name": "All Monitor Any hour - Website & Admin panel",
    "image": "/portfolio/allmonitor.png",
    "description": "Database Website for keep Track of Different sites with advertisement and other features. Admin panel for manage the website.",
    "tags": [
      "php",
      "laravel",
      "mysql",
      "javascript",
      "jquery",
      "ajax",
      "bootstrap",
      "seo"
    ],
    "demo": "https://allmonitorsanyhour.com/"
  },
  {
    "id": 2,
    "name": "Antaheen Foundation Website & Admin Panel",
    "image": "/portfolio/antaheen.png",
    "description": "Official website of Antaheen Foundation. This project is fully responsive & customizable from admin panel.",
    "tags": [
      "php",
      "laravel",
      "mysql",
      "javascript",
      "jquery",
      "ajax",
      "bootstrap"
    ],
    "demo": "https://www.antaheenfoundation.org/"

  }
  
]